kryptic_cypher-0.1.1.dist-info/METADATA
kryptic_cypher-0.1.1.dist-info/WHEEL
kryptic_cypher-0.1.1.dist-info/entry_points.txt
kryptic_cypher-0.1.1.dist-info/licenses/LICENSE
kryptic_cypher/__init__.py
kryptic_cypher/__main__.py
kryptic_cypher/app.py
kryptic_cypher/cypher.py
kryptic_cypher-0.1.1.dist-info/RECORD
