Metadata-Version: 2.1
Name: kryptic_cypher
Version: 0.1.1
Summary: A simple encryption library that lets you play with insecure common encryption algos
Keywords: encyrption,cli
Author-Email: Andres Carrera <andreshcar@live.com>
Classifier: Intended Audience :: Information Technology
Classifier: Intended Audience :: Developers
Classifier: Operating System :: OS Independent
Classifier: Topic :: Software Development :: Libraries :: Python Modules
Classifier: Topic :: Software Development :: Libraries
Classifier: Topic :: Software Development
Classifier: License :: OSI Approved :: MIT License
Classifier: Programming Language :: Python :: 3 :: Only
Classifier: Programming Language :: Python :: 3.10
Classifier: Programming Language :: Python :: 3.11
Classifier: Programming Language :: Python :: 3.12
Project-URL: Homepage, https://github.com/carrera-dev-consulting/kryptic-cypher
Project-URL: Documentation, https://consulting.gxldcptrick.dev/kryptic-cypher
Project-URL: Repository, https://github.com/carrera-dev-consulting/kryptic-cypher
Project-URL: Issues, https://github.com/carrera-dev-consulting/kryptic-cypher/issues
Project-URL: Changelog, https://github.com/carrera-dev-consulting/kryptic-cypher/releases
Requires-Python: >=3.10
Requires-Dist: pydantic>=2.9.2
Requires-Dist: click>=8.1.7
